Metadata-Version: 2.1
Name: sisua
Version: 0.4.3
Summary: SemI-SUpervised generative Autoencoder for single cell data
Home-page: https://github.com/trungnt13/sisua
Author: University of Eastern Finland
Author-email: trung@imito.ai
License: MIT license
Keywords: sisua
Platform: UNKNOWN
Classifier: Development Status :: 4 - Beta
Classifier: License :: OSI Approved :: MIT License
Classifier: Natural Language :: English
Classifier: Programming Language :: Python :: 3.6
Classifier: Operating System :: MacOS :: MacOS X
Classifier: Operating System :: Microsoft :: Windows
Classifier: Operating System :: POSIX :: Linux
Classifier: Topic :: Scientific/Engineering :: Artificial Intelligence
Classifier: Topic :: Scientific/Engineering :: Bio-Informatics
Classifier: Intended Audience :: Developers
Classifier: Intended Audience :: Education
Classifier: Intended Audience :: Science/Research
Requires-Dist: odin-ai (==1.1.1)
Requires-Dist: seaborn (>=0.9)
Requires-Dist: pandas
Requires-Dist: scanpy (==1.4.4)
